dearpygui_forms/__init__.py
dearpygui_forms/dpg_form.py
dearpygui_forms/exceptions.py
dearpygui_forms/models.py
dearpygui_forms/widgets.py
dearpygui_forms-0.2.1.dist-info/METADATA
dearpygui_forms-0.2.1.dist-info/WHEEL
dearpygui_forms-0.2.1.dist-info/RECORD
