Metadata-Version: 2.4
Name: dearpygui-forms
Version: 0.2.1
Summary: Dearpygui extention for autogeneration forms powered by pydantic.
Project-URL: homepage, https://github.com/vlewicki/dearpygui-forms
Author-email: Valentin Lewicki <vlewicki@vlewicki.ru>
Requires-Python: >=3.10
Requires-Dist: dearpygui>=2.0.0
Requires-Dist: loguru>=0.7.3
Requires-Dist: pydantic>=2.11.7
